whatsfly/__init__.py
whatsfly/featureflags.py
whatsfly/whatsapp.py
whatsfly/whatsmeow.py
whatsfly/dependencies/README.md
whatsfly/dependencies/__init__.py
whatsfly/dependencies/build.sh
whatsfly/dependencies/builder.py
whatsfly/dependencies/github_actions_download.py
whatsfly/dependencies/go.mod
whatsfly/dependencies/go.sum
whatsfly/dependencies/main.go
whatsfly/dependencies/wapp.h
whatsfly/proto/__init__.py
whatsfly/proto/generate_protos.sh
whatsfly/proto/waAdv/WAAdv.pb.raw
whatsfly/proto/waAdv/WAAdv.proto
whatsfly/proto/waAdv/WAAdv_pb2.py
whatsfly/proto/waAdv/__init__.py
whatsfly/proto/waArmadilloApplication/WAArmadilloApplication.pb.raw
whatsfly/proto/waArmadilloApplication/WAArmadilloApplication.proto
whatsfly/proto/waArmadilloApplication/WAArmadilloApplication_pb2.py
whatsfly/proto/waArmadilloApplication/__init__.py
whatsfly/proto/waArmadilloBackupMessage/WAArmadilloBackupMessage.pb.raw
whatsfly/proto/waArmadilloBackupMessage/WAArmadilloBackupMessage.proto
whatsfly/proto/waArmadilloBackupMessage/WAArmadilloBackupMessage_pb2.py
whatsfly/proto/waArmadilloBackupMessage/__init__.py
whatsfly/proto/waArmadilloICDC/WAArmadilloICDC.pb.raw
whatsfly/proto/waArmadilloICDC/WAArmadilloICDC.proto
whatsfly/proto/waArmadilloICDC/WAArmadilloICDC_pb2.py
whatsfly/proto/waArmadilloICDC/__init__.py
whatsfly/proto/waArmadilloXMA/WAArmadilloXMA.pb.raw
whatsfly/proto/waArmadilloXMA/WAArmadilloXMA.proto
whatsfly/proto/waArmadilloXMA/WAArmadilloXMA_pb2.py
whatsfly/proto/waArmadilloXMA/__init__.py
whatsfly/proto/waCert/WACert.pb.raw
whatsfly/proto/waCert/WACert.proto
whatsfly/proto/waCert/WACert_pb2.py
whatsfly/proto/waCert/__init__.py
whatsfly/proto/waChatLockSettings/WAProtobufsChatLockSettings.pb.raw
whatsfly/proto/waChatLockSettings/WAProtobufsChatLockSettings.proto
whatsfly/proto/waChatLockSettings/WAProtobufsChatLockSettings_pb2.py
whatsfly/proto/waChatLockSettings/__init__.py
whatsfly/proto/waCommon/WACommon.pb.raw
whatsfly/proto/waCommon/WACommon.proto
whatsfly_labfox-0.3.2.dist-info/licenses/LICENSE
whatsfly_labfox-0.3.2.dist-info/METADATA
whatsfly_labfox-0.3.2.dist-info/WHEEL
whatsfly_labfox-0.3.2.dist-info/top_level.txt
whatsfly_labfox-0.3.2.dist-info/RECORD
