Metadata-Version: 2.4
Name: whatsfly_labfox
Version: 0.3.2
Summary: Whatsapp Web wrapper in Python, without webdrivers
Home-page: https://whatsfly.labfox.fr
Author: LabFox
Author-email: Labfox <consockbind@gmail.com>, Doy Bachtiar <adityabachtiar996@gmail.com>, Otamay <mauricio@ulisse.io>, Ivo Bellin Salarin <ivo@nilleb.com>
Project-URL: Homepage, https://github.com/Labfox/whatsfly
Project-URL: Issues, https://github.com/Labfox/whatsfly/issues
Classifier: Programming Language :: Python :: 3
Classifier: License :: OSI Approved :: MIT License
Classifier: Operating System :: Unix
Classifier: Operating System :: POSIX :: Linux
Classifier: Operating System :: MacOS :: MacOS X
Classifier: Operating System :: Microsoft :: Windows
Classifier: Topic :: Communications
Classifier: Topic :: Communications :: Chat
Requires-Python: >=3.12
License-File: LICENSE
Requires-Dist: types-pyyaml
Requires-Dist: setuptools
Requires-Dist: requests
Requires-Dist: qrcode
Requires-Dist: protobuf
Dynamic: author
Dynamic: home-page
Dynamic: license-file
